<author lang="en" gender="male" age_group="20s">	<conversations count="13">		<conversation id="5a7c33d417ae8f491a2b4ad2ef931b33">			&lt;a href="http://en.pan.netcom/go/out/url=http%3A%2F%2Fwww.bytewiki.com%2Fmotorola-mobility-apparently-won-an-injunction-against-apple-in-germany-court-over-two-patents%2F"target="_blank" rel="nofollow"&gt;;http://www.bytewiki.com/motorola-mobility-apparently-won-an-injunction-against-apple-in-germany-court-over-two-patents/&lt;/a&gt;; 
&lt;br /&gt;;&lt;br /&gt;;Motorola Mobility apparently Won an Injunction against Apple in Germany Court over two Patents		</conversation>		<conversation id="2235a61441e6bca9f14324b7ae5855d2">			&lt;a href="http://en.pan.netcom/go/out/url=http%3A%2F%2Fwww.bytewiki.com%2Fispy-software-can-read-texts-and-steal-passwords-video%2F"target="_blank" rel="nofollow"&gt;;http://www.bytewiki.com/ispy-software-can-read-texts-and-steal-passwords-video/&lt;/a&gt;; 
&lt;br /&gt;;&lt;br /&gt;;iSpy software can read texts and steal passwords (video)		</conversation>		<conversation id="595687ea238366109b3184a09f2cce85">			&lt;a href="http://en.pan.netcom/go/out/url=http%3A%2F%2Fwww.bytewiki.com%2Fmicrosoft-approved-windows-phone-7-unlocker-chevronwp7-goes-live%2F"target="_blank" rel="nofollow"&gt;;http://www.bytewiki.com/microsoft-approved-windows-phone-7-unlocker-chevronwp7-goes-live/&lt;/a&gt;; 
&lt;br /&gt;;&lt;br /&gt;;Microsoft Approved Windows Phone 7 Unlocker ChevronWP7 goes Live		</conversation>		<conversation id="93115e83ce7a7ac63f6f875d25adfda6">			&lt;a href="http://en.pan.netcom/go/out/url=http%3A%2F%2Fbytewiki.com"target="_blank" rel="nofollow"&gt;;http://bytewiki.com&lt;/a&gt;; 
&lt;br /&gt;;&lt;br /&gt;;Bytewiki is a technology blog about social media, software, technology news, reviews, and tutorials.		</conversation>		<conversation id="1110d4683de6d575456aa085a46dd1a9">			&lt;a href="http://en.pan.netcom/go/out/url=http%3A%2F%2Ffeedproxy.google.com%2F%7Er%2Fbytewiki%2F%7E3%2FzH5zFK3KPfw%2F"target="_blank" rel="nofollow"&gt;;http://feedproxy.google.com/~r/bytewiki/~3/zH5zFK3KPfw/&lt;/a&gt;; 
&lt;br /&gt;;&lt;br /&gt;;Motorola Mobility apparently Won an Injunction against Apple in Germany Court over two Patents		</conversation>		<conversation id="407e1929e29200460df41939920f87db">			&lt;a href="http://en.pan.netcom/go/out/url=http%3A%2F%2Fwww.bytewiki.com%2Fgoogle-for-android-updated-2-1-1-lost-widget-is-back%2F"target="_blank" rel="nofollow"&gt;;http://www.bytewiki.com/google-for-android-updated-2-1-1-lost-widget-is-back/&lt;/a&gt;; 
&lt;br /&gt;;&lt;br /&gt;;Google+ For Android Updated (2.1.1), Lost Widget Is Back		</conversation>		<conversation id="65f0c358e22674502c48afa0f378bf8e">			&lt;a href="http://en.pan.netcom/go/out/url=http%3A%2F%2Ffeedproxy.google.com%2F%7Er%2Fbytewiki%2F%7E3%2FuHGsU0rKWoI%2F"target="_blank" rel="nofollow"&gt;;http://feedproxy.google.com/~r/bytewiki/~3/uHGsU0rKWoI/&lt;/a&gt;; 
&lt;br /&gt;;&lt;br /&gt;;Google+ For Android Updated (2.1.1), Lost Widget Is Back		</conversation>		<conversation id="154d971cda7b683ebb2e5444b80ad6c6">			&lt;a href="http://en.pan.netcom/go/out/url=http%3A%2F%2Ffeedproxy.google.com%2F%7Er%2Fbytewiki%2F%7E3%2FskqaoJ3tHhE%2F"target="_blank" rel="nofollow"&gt;;http://feedproxy.google.com/~r/bytewiki/~3/skqaoJ3tHhE/&lt;/a&gt;; 
&lt;br /&gt;;&lt;br /&gt;;How to Activate Windows 3D Preview Mode Using Mouse Cursor		</conversation>		<conversation id="a0218f67fd3728833c5ef4da6995fe10">			&lt;a href="http://en.pan.netcom/go/out/url=http%3A%2F%2Fwww.bytewiki.com%2Flost-interview-with-steve-jobs-to-be-shown-on-big-screen%2F"target="_blank" rel="nofollow"&gt;;http://www.bytewiki.com/lost-interview-with-steve-jobs-to-be-shown-on-big-screen/&lt;/a&gt;; 
&lt;br /&gt;;&lt;br /&gt;;‘Lost interview’ with Steve Jobs to be shown on big screen		</conversation>		<conversation id="22ffe950c815ddbbb74bb8b79f2cebb7">			&lt;a href="http://en.pan.netcom/go/out/url=http%3A%2F%2Ffeedproxy.google.com%2F%7Er%2Fbytewiki%2F%7E3%2Fo_JuZuyrrSM%2F"target="_blank" rel="nofollow"&gt;;http://feedproxy.google.com/~r/bytewiki/~3/o_JuZuyrrSM/&lt;/a&gt;; 
&lt;br /&gt;;&lt;br /&gt;;‘Lost interview’ with Steve Jobs to be shown on big screen		</conversation>		<conversation id="1ac53a338050c0d18c5c398c103eb49a">			&lt;a href="http://en.pan.netcom/go/out/url=http%3A%2F%2Ffeedproxy.google.com%2F%7Er%2Fbytewiki%2F%7E3%2Fo_JuZuyrrSM%2F"target="_blank" rel="nofollow"&gt;;http://feedproxy.google.com/~r/bytewiki/~3/o_JuZuyrrSM/&lt;/a&gt;; 
&lt;br /&gt;;&lt;br /&gt;;‘Lost interview’ with Steve Jobs to be shown on big screen		</conversation>		<conversation id="5406fd44509cdc71af22938edf6576bb">			&lt;a href="http://en.pan.netcom/go/out/url=http%3A%2F%2Fwww.bytewiki.com%2Fapple-is-turned-down-by-cbs-over-apple-tv-ad-based-deal%2F"target="_blank" rel="nofollow"&gt;;http://www.bytewiki.com/apple-is-turned-down-by-cbs-over-apple-tv-ad-based-deal/&lt;/a&gt;; 
&lt;br /&gt;;&lt;br /&gt;;Apple is Turned down by CBS over Apple TV ad-based deal		</conversation>		<conversation id="363d581b2580cec1b12ddce8ded9b887">			&lt;a href="http://en.pan.netcom/go/out/url=http%3A%2F%2Ffeedproxy.google.com%2F%7Er%2Fbytewiki%2F%7E3%2F1KRSkQlPwNM%2F"target="_blank" rel="nofollow"&gt;;http://feedproxy.google.com/~r/bytewiki/~3/1KRSkQlPwNM/&lt;/a&gt;; 
&lt;br /&gt;;&lt;br /&gt;;Apple is Turned down by CBS over Apple TV ad-based deal		</conversation>	</conversations></author>