<author lang="en" gender="female" age_group="30s">	<conversations count="3">		<conversation id="530d0fd8446a4092c23d6e8dd49a4cde">			cant be assed with crap.... so dont be a dingbat x oooooooshhht xxxxx		</conversation>		<conversation id="d28b2cd1a44ded7b74e423f68ff394a6">			wha is it wae me an hajs? anywhhhoooooooo this sites bad christ lol x		</conversation>		<conversation id="39cbceeb27b240ff4320017cda9e8e45">			as u all stoopid..... feckn haj nah		</conversation>	</conversations></author>