<author lang="en" gender="male" age_group="30s">	<conversations count="12">		<conversation id="288d3f7bc662fe3f33cdb4807096b17a">			Hey hey!
&lt;br /&gt;;&lt;br /&gt;;My blog has now been moved to the main site at &lt;a href="http://en.pan.netcom/go/out/url=http%3A%2F%2Fwww.socialnatural.com"target="_blank" rel="nofollow"&gt;;http://www.socialnatural.com&lt;/a&gt;;, and it has been completely redone in a whole new way for better reader and user experience!
&lt;br /&gt;;&lt;br /&gt;;Check it out now!
&lt;br /&gt;;&lt;br /&gt;;&lt;a href="http://en.pan.netcom/go/out/url=http%3A%2F%2Fwww.socialnatural.com"target="_blank" rel="nofollow"&gt;;http://www.socialnatural.com&lt;/a&gt;;		</conversation>		<conversation id="5d1ccb28314d5d9f84d3621e522df63f">			&lt;a href="http://en.pan.netcom/go/out/url=http%3A%2F%2Fwww.socialnatural.com%2F2011%2Fwhat-to-wear-to-attract-women-on-halloween%2F"target="_blank" rel="nofollow"&gt;;http://www.socialnatural.com/2011/what-to-wear-to-attract-women-on-halloween/&lt;/a&gt;; 
&lt;br /&gt;;&lt;br /&gt;;If you’re still trying to figure out on a Halloween costume that will attract women like a moth to a flame, I got a Halloween special treat for you...		</conversation>		<conversation id="c40338a14717d80d2f1a749be9df7ac7">			&lt;a href="http://en.pan.netcom/go/out/url=http%3A%2F%2Fwww.socialnatural.com%2F2011%2Fseduction-community-backfires%2F"target="_blank" rel="nofollow"&gt;;http://www.socialnatural.com/2011/seduction-community-backfires/&lt;/a&gt;; 
&lt;br /&gt;;&lt;br /&gt;;Have you ever really wondered why some people just get dating and meeting women the very first few times they learned this stuff and start getting immediate results, while others learned like forever and going out…but are still struggling?		</conversation>		<conversation id="3ccf39827ba49731f6ae2686280c2d3b">			&lt;a href="http://en.pan.netcom/go/out/url=http%3A%2F%2Fwww.socialnatural.com%2F2011%2Fimportance-of-being-social%2F"target="_blank" rel="nofollow"&gt;;http://www.socialnatural.com/2011/importance-of-being-social/&lt;/a&gt;; 
&lt;br /&gt;;&lt;br /&gt;;Now why do we need to learn how to be social?		</conversation>		<conversation id="ef58522f4372be1259b9dc51fd1f8fe2">			&lt;a href="http://en.pan.netcom/go/out/url=http%3A%2F%2Fwww.socialnatural.com%2F2011%2Fspecial-thanksgiving%2F"target="_blank" rel="nofollow"&gt;;http://www.socialnatural.com/2011/special-thanksgiving/&lt;/a&gt;; 
&lt;br /&gt;;&lt;br /&gt;;Gobble!  Gobblely doo!  Gobble!  Gobble away!  That’s right…Happy Thanksgiving!  Hope you’re enjoying your...		</conversation>		<conversation id="f7b84a5c9357edbdbfccd997776fb5b4">			&lt;a href="http://en.pan.netcom/go/out/url=http%3A%2F%2Fwww.socialnatural.com%2F2011%2Fbecome-the-most-social-person-you-can-be%2F"target="_blank" rel="nofollow"&gt;;http://www.socialnatural.com/2011/become-the-most-social-person-you-can-be/&lt;/a&gt;; 
&lt;br /&gt;;&lt;br /&gt;;How can you improve your social skills NOW to become the most social person you can be…when you are not socially skilled in the first place to socialize effectively to build your social skills?		</conversation>		<conversation id="4e2735231c0130de409a979ce2c69a34">			&lt;a href="http://en.pan.netcom/go/out/url=http%3A%2F%2Fwww.socialnatural.com%2F2011%2Fhappy-holidays%2F"target="_blank" rel="nofollow"&gt;;http://www.socialnatural.com/2011/happy-holidays/&lt;/a&gt;; 
&lt;br /&gt;;&lt;br /&gt;;Ahhh, yes…Christmas time is here!  Can’t remember the last time Christmas was on a Sunday…that means Christmas Eve on a Saturday…		</conversation>		<conversation id="d3ffa2e03c68a90489d2b851cdc134d">			&lt;a href="http://en.pan.netcom/go/out/url=http%3A%2F%2Fwww.socialnatural.com%2F2011%2Flast-minute-reflection-upon-the-year%2F"target="_blank" rel="nofollow"&gt;;http://www.socialnatural.com/2011/last-minute-reflection-upon-the-year/&lt;/a&gt;; 
&lt;br /&gt;;&lt;br /&gt;;Once again…this is the time of the year, where you should reflect on what has happened, what has changed in your life, and how you plan on moving forward in your...		</conversation>		<conversation id="86f7ed85c18e819cc68fbf1fe9e2587">			&lt;a href="http://en.pan.netcom/go/out/url=http%3A%2F%2Fwww.socialnatural.com%2F2012%2Fpredicting-identity-extroversion-and-introversion-1%2F"target="_blank" rel="nofollow"&gt;;http://www.socialnatural.com/2012/predicting-identity-extroversion-and-introversion-1/&lt;/a&gt;; 
&lt;br /&gt;;&lt;br /&gt;;Have you ever wondered WHY some people are naturally prone to being social than others and have a much more extroverted tendency?		</conversation>		<conversation id="9a7c67ceb833d4f2317ee3b94502f56a">			&lt;a href="http://en.pan.netcom/go/out/url=http%3A%2F%2Fwww.socialnatural.com%2F2012%2Fpredicting-identity-extroversion-and-introversion-2%2F"target="_blank" rel="nofollow"&gt;;http://www.socialnatural.com/2012/predicting-identity-extroversion-and-introversion-2/&lt;/a&gt;; 
&lt;br /&gt;;&lt;br /&gt;;Now here’s the second-part to the concluding &quot;Predicting Identity: Extroversion and Introversion&quot;...		</conversation>		<conversation id="e2f34a20b6db63dcdc170e6df5aa957a">			Welcome to the Social Natural Lifestyle!  I am starting the Social Natural Lifestyle as an easy way for you...		</conversation>		<conversation id="1341e8b925778495c96a391e0fb0dbe1">			&lt;a href="http://en.pan.netcom/go/out/url=http%3A%2F%2Fwww.socialnatural.com%2F2008%2Fwho-is-gabriel-angelo%2F"target="_blank" rel="nofollow"&gt;;http://www.socialnatural.com/2008/who-is-gabriel-angelo/&lt;/a&gt;; 
&lt;br /&gt;;&lt;br /&gt;;Do you find yourself to be NOT really a social guy that can meet women and get them attracted to you?		</conversation>	</conversations></author>